setup.cfg
setup.py
matpot/matpot.py
matpot.py.egg-info/PKG-INFO
matpot.py.egg-info/SOURCES.txt
matpot.py.egg-info/dependency_links.txt
matpot.py.egg-info/top_level.txt