Metadata-Version: 2.1
Name: matpot.py
Version: 0.2
Summary: custom module for personal use
Author: cMepTHuk58
Author-email: evgenyzach@mail.ru
